foldermap/__init__.py
foldermap/cli.py
foldermap/core.py
foldermap-0.1.6.dist-info/LICENSE
foldermap-0.1.6.dist-info/METADATA
foldermap-0.1.6.dist-info/WHEEL
foldermap-0.1.6.dist-info/entry_points.txt
foldermap-0.1.6.dist-info/top_level.txt
foldermap-0.1.6.dist-info/RECORD
