Metadata-Version: 2.1
Name: foldermap
Version: 0.1.6
Summary: A tool for mapping files and folders to markdown documentation
Home-page: https://github.com/newrachael/foldermap
Author: Raykim
Author-email: enro2414@gmail.com
Classifier: Programming Language :: Python :: 3
Classifier: Programming Language :: Python :: 3.6
Classifier: Programming Language :: Python :: 3.7
Classifier: Programming Language :: Python :: 3.8
Classifier: Programming Language :: Python :: 3.9
Classifier: License :: OSI Approved :: MIT License
Classifier: Operating System :: OS Independent
Classifier: Topic :: Documentation
Classifier: Topic :: Software Development :: Documentation
Classifier: Topic :: Utilities
Requires-Python: >=3.6
License-File: LICENSE
Requires-Dist: pathspec>=0.9.0
